data_manifestor/__init__.py
data_manifestor/core.py
data_manifestor/exceptions.py
data_manifestor/models/__init__.py
data_manifestor/models/schemas.py
data_manifestor/paths.py
data_manifestor-0.5.6.dist-info/LICENSE
data_manifestor-0.5.6.dist-info/WHEEL
data_manifestor-0.5.6.dist-info/METADATA
data_manifestor-0.5.6.dist-info/RECORD
