Metadata-Version: 2.1
Name: data-manifestor
Version: 0.5.6
Summary: Awesome `data_manifestor` is a Python cli/package created with https://github.com/TezRomacH/python-package-template
Home-page: https://github.com/data_manifestor/data_manifestor
License: MIT
Author: data_manifestor
Author-email: chrism@alleninstitute.org
Requires-Python: >=3.9,<4.0
Classifier: Development Status :: 3 - Alpha
Classifier: Intended Audience :: Developers
Classifier: License :: OSI Approved :: MIT License
Classifier: Operating System :: OS Independent
Classifier: Programming Language :: Python :: 3
Classifier: Programming Language :: Python :: 3.10
Classifier: Programming Language :: Python :: 3.9
Classifier: Topic :: Software Development :: Libraries :: Python Modules
Requires-Dist: PyYAML (==6.0)
Requires-Dist: dparse (==0.5.2)
Requires-Dist: marshmallow (>=3.17.0,<4.0.0)
Requires-Dist: np-lims-tk (>=0.9.1,<0.10.0)
Requires-Dist: rich (==12.5.1)
Requires-Dist: typer (==0.6.1)
Project-URL: Repository, https://github.com/data_manifestor/data_manifestor
